LigPrepper/__init__.py
LigPrepper/main.py
LigPrepper-0.5.0.dist-info/LICENSE
LigPrepper-0.5.0.dist-info/METADATA
LigPrepper-0.5.0.dist-info/WHEEL
LigPrepper-0.5.0.dist-info/top_level.txt
LigPrepper-0.5.0.dist-info/RECORD
