Metadata-Version: 2.1
Name: LigPrepper
Version: 0.5.0
Summary: Simple program to quickly prepare ligand 3d SDF/MOL2/PDBQT from smiles
Home-page: https://github.com/aakognole/ligprepper
Author: Abhishek Kognole
Author-email: aakognole@gmail.com
Project-URL: Bug Tracker, https://github.com/aakognole/ligprepper/issues
Classifier: Programming Language :: Python :: 3
Classifier: License :: OSI Approved :: MIT License
Classifier: Operating System :: OS Independent
Requires-Python: >=3.9
License-File: LICENSE
Requires-Dist: rdkit
